gfold/__init__.py
gfold/__main__.py
gfold/cli.py
gfold/config.py
gfold/solver.py
gfold/visualization.py
gfold-0.1.2.dist-info/METADATA
gfold-0.1.2.dist-info/WHEEL
gfold-0.1.2.dist-info/entry_points.txt
gfold-0.1.2.dist-info/top_level.txt
gfold-0.1.2.dist-info/RECORD
