Metadata-Version: 2.4
Name: gfold
Version: 0.1.2
Summary: G-FOLD: Fuel Optimal Large Divert Guidance Algorithm
Author-email: Samu Toljamo <samu.toljamo@gmail.com>
Project-URL: Homepage, https://github.com/samutoljamo/g-fold
Project-URL: Bug Tracker, https://github.com/samutoljamo/g-fold/issues
Classifier: Programming Language :: Python :: 3
Classifier: License :: OSI Approved :: MIT License
Classifier: Operating System :: OS Independent
Requires-Python: >=3.7
Requires-Dist: cvxpy
Requires-Dist: cvxpygen
Requires-Dist: matplotlib
Requires-Dist: numpy
Requires-Dist: jinja2
